{
  "$schema": "https://developer.microsoft.com/json-schemas/fabric/item/report/definition/visualContainer/2.2.0/schema.json",
  "name": "0bd648c5b265b56aa015",
  "position": {
    "x": 252.27323628219486,
    "y": 170.57110862262039,
    "z": 7000,
    "height": 110.36954087346025,
    "width": 237.93952967525198,
    "tabOrder": 7000
  },
  "visual": {
    "visualType": "card",
    "query": {
      "queryState": {
        "Values": {
          "projections": [
            {
              "field": {
                "Measure": {
                  "Expression": {
                    "SourceRef": {
                      "Entity": "_Medidas"
                    }
                  },
                  "Property": "06 Vendas C/ Vnd"
                }
              },
              "queryRef": "_Medidas.06 Vendas C/ Vnd"
            }
          ]
        }
      },
      "sortDefinition": {
        "sort": [
          {
            "field": {
              "Measure": {
                "Expression": {
                  "SourceRef": {
                    "Entity": "_Medidas"
                  }
                },
                "Property": "06 Vendas C/ Vnd"
              }
            },
            "direction": "Descending"
          }
        ],
        "isDefaultSort": true
      }
    },
    "drillFilterOtherVisuals": true
  }
}